{"char":null,"freq":832,"left":{"char":null,"freq":342,"left":{"char":null,"freq":161,"left":{"char":null,"freq":80,"left":{"char":"t","freq":40,"left":null,"right":null},"right":{"char":"r","freq":40,"left":null,"right":null}},"right":{"char":null,"freq":81,"left":{"char":null,"freq":40,"left":{"char":"p","freq":20,"left":null,"right":null},"right":{"char":null,"freq":20,"left":{"char":null,"freq":10,"left":{"char":"S","freq":5,"left":null,"right":null},"right":{"char":">","freq":5,"left":null,"right":null}},"right":{"char":null,"freq":10,"left":{"char":"(","freq":5,"left":null,"right":null},"right":{"char":null,"freq":5,"left":{"char":null,"freq":2,"left":{"char":"x","freq":1,"left":null,"right":null},"right":{"char":";","freq":1,"left":null,"right":null}},"right":{"char":"A","freq":3,"left":null,"right":null}}}}},"right":{"char":"s","freq":41,"left":null,"right":null}}},"right":{"char":null,"freq":181,"left":{"char":null,"freq":87,"left":{"char":"o","freq":43,"left":null,"right":null},"right":{"char":"i","freq":44,"left":null,"right":null}},"right":{"char":null,"freq":94,"left":{"char":null,"freq":46,"left":{"char":null,"freq":22,"left":{"char":"w","freq":11,"left":null,"right":null},"right":{"char":"-","freq":11,"left":null,"right":null}},"right":{"char":"l","freq":24,"left":null,"right":null}},"right":{"char":null,"freq":48,"left":{"char":"\r","freq":24,"left":null,"right":null},"right":{"char":"\n","freq":24,"left":null,"right":null}}}}},"right":{"char":null,"freq":490,"left":{"char":null,"freq":223,"left":{"char":null,"freq":101,"left":{"char":null,"freq":49,"left":{"char":null,"freq":24,"left":{"char":"f","freq":11,"left":null,"right":null},"right":{"char":".","freq":13,"left":null,"right":null}},"right":{"char":"c","freq":25,"left":null,"right":null}},"right":{"char":"a","freq":52,"left":null,"right":null}},"right":{"char":null,"freq":122,"left":{"char":null,"freq":56,"left":{"char":"u","freq":26,"left":null,"right":null},"right":{"char":null,"freq":30,"left":{"char":null,"freq":14,"left":{"char":"m","freq":7,"left":null,"right":null},"right":{"char":null,"freq":7,"left":{"char":null,"freq":3,"left":{"char":"F","freq":1,"left":null,"right":null},"right":{"char":"2","freq":2,"left":null,"right":null}},"right":{"char":null,"freq":4,"left":{"char":"3","freq":2,"left":null,"right":null},"right":{"char":"C","freq":2,"left":null,"right":null}}}},"right":{"char":"b","freq":16,"left":null,"right":null}}},"right":{"char":null,"freq":66,"left":{"char":null,"freq":32,"left":{"char":null,"freq":16,"left":{"char":"g","freq":8,"left":null,"right":null},"right":{"char":")","freq":8,"left":null,"right":null}},"right":{"char":null,"freq":16,"left":{"char":null,"freq":8,"left":{"char":null,"freq":4,"left":{"char":"E","freq":2,"left":null,"right":null},"right":{"char":"D","freq":2,"left":null,"right":null}},"right":{"char":null,"freq":4,"left":{"char":"H","freq":2,"left":null,"right":null},"right":{"char":"O","freq":2,"left":null,"right":null}}},"right":{"char":null,"freq":8,"left":{"char":null,"freq":4,"left":{"char":"R","freq":2,"left":null,"right":null},"right":{"char":"I","freq":2,"left":null,"right":null}},"right":{"char":null,"freq":4,"left":{"char":"j","freq":2,"left":null,"right":null},"right":{"char":"z","freq":2,"left":null,"right":null}}}}},"right":{"char":"n","freq":34,"left":null,"right":null}}}},"right":{"char":null,"freq":267,"left":{"char":" ","freq":124,"left":null,"right":null},"right":{"char":null,"freq":143,"left":{"char":"e","freq":71,"left":null,"right":null},"right":{"char":null,"freq":72,"left":{"char":null,"freq":34,"left":{"char":"k","freq":17,"left":null,"right":null},"right":{"char":null,"freq":17,"left":{"char":null,"freq":8,"left":{"char":null,"freq":4,"left":{"char":"v","freq":2,"left":null,"right":null},"right":{"char":null,"freq":2,"left":{"char":"1","freq":1,"left":null,"right":null},"right":{"char":"4","freq":1,"left":null,"right":null}}},"right":{"char":null,"freq":4,"left":{"char":null,"freq":2,"left":{"char":"B","freq":1,"left":null,"right":null},"right":{"char":"K","freq":1,"left":null,"right":null}},"right":{"char":null,"freq":2,"left":{"char":"/","freq":1,"left":null,"right":null},"right":{"char":"N","freq":1,"left":null,"right":null}}}},"right":{"char":"y","freq":9,"left":null,"right":null}}},"right":{"char":null,"freq":38,"left":{"char":"d","freq":19,"left":null,"right":null},"right":{"char":"h","freq":19,"left":null,"right":null}}}}}}}